LUCY/X.npy
LUCY/Y.npy
LUCY/__init__.py
LUCY/app.py
LUCY/data_collection.py
LUCY/data_preprocessing.py
LUCY/eth_lstm_best_strong_greatest_model.h5
LUCY/eth_price_data.csv
LUCY/hyperparameter.py
LUCY/model_evaluation.py
LUCY/model_training.py
LUCY/scaler_custom.pkl
LUCY/setup.py
SourceFiles/__init__.py
SourceFiles/app.py
SourceFiles/data_collection.py
SourceFiles/data_preprocessing.py
SourceFiles/hyperparameter.py
SourceFiles/model_evaluation.py
SourceFiles/model_training.py
SourceFiles/setup.py
MyFriendLUCY_1-1.0.3.dist-info/METADATA
MyFriendLUCY_1-1.0.3.dist-info/WHEEL
MyFriendLUCY_1-1.0.3.dist-info/entry_points.txt
MyFriendLUCY_1-1.0.3.dist-info/top_level.txt
MyFriendLUCY_1-1.0.3.dist-info/RECORD
